entrez_fetcher/__init__.py
entrez_fetcher/assembly_store.py
entrez_fetcher/entrez_eutils.py
entrez_fetcher/genome_store.py
entrez_fetcher/models.py
entrez_fetcher/utils.py
entrez_fetcher-2023.9.4.dist-info/LICENSE
entrez_fetcher-2023.9.4.dist-info/METADATA
entrez_fetcher-2023.9.4.dist-info/WHEEL
entrez_fetcher-2023.9.4.dist-info/RECORD
