Metadata-Version: 2.1
Name: entrez-fetcher
Version: 2023.9.4
Summary: 
Author: Nicolas Cellier
Author-email: contact@nicolas-cellier.net
Requires-Python: >=3.9,<3.12
Classifier: Programming Language :: Python :: 3
Classifier: Programming Language :: Python :: 3.9
Classifier: Programming Language :: Python :: 3.10
Classifier: Programming Language :: Python :: 3.11
Requires-Dist: appdirs (>=1.4.4,<2.0.0)
Requires-Dist: biopython (>=1.79,<2.0)
Requires-Dist: filelock (>=3.12.3,<4.0.0)
Requires-Dist: loguru (>=0.7.0,<0.8.0)
Requires-Dist: montydb (>=2.4.0,<3.0.0)
Requires-Dist: more-itertools (>=10.1.0,<11.0.0)
Requires-Dist: polars (>=0.19.1,<0.20.0)
Requires-Dist: pooch (>=1.7.0,<2.0.0)
Requires-Dist: pydantic (<2.0.0)
Requires-Dist: tqdm (>=4.66.1,<5.0.0)
Requires-Dist: uplink (>=0.9.7,<0.10.0)
